cardano_clusterlib/__init__.py
cardano_clusterlib/address_group.py
cardano_clusterlib/clusterlib.py
cardano_clusterlib/clusterlib_helpers.py
cardano_clusterlib/clusterlib_klass.py
cardano_clusterlib/consts.py
cardano_clusterlib/exceptions.py
cardano_clusterlib/genesis_group.py
cardano_clusterlib/gov_action_group.py
cardano_clusterlib/gov_committee_group.py
cardano_clusterlib/gov_drep_group.py
cardano_clusterlib/gov_group.py
cardano_clusterlib/gov_vote_group.py
cardano_clusterlib/helpers.py
cardano_clusterlib/key_group.py
cardano_clusterlib/legacy_gov_group.py
cardano_clusterlib/node_group.py
cardano_clusterlib/py.typed
cardano_clusterlib/query_group.py
cardano_clusterlib/stake_address_group.py
cardano_clusterlib/stake_pool_group.py
cardano_clusterlib/structs.py
cardano_clusterlib/transaction_group.py
cardano_clusterlib/txtools.py
cardano_clusterlib/types.py
cardano_clusterlib-0.9.9.dist-info/licenses/LICENSE
cardano_clusterlib-0.9.9.dist-info/METADATA
cardano_clusterlib-0.9.9.dist-info/WHEEL
cardano_clusterlib-0.9.9.dist-info/top_level.txt
cardano_clusterlib-0.9.9.dist-info/RECORD
