Metadata-Version: 2.4
Name: cardano-clusterlib
Version: 0.9.9
Summary: Python wrapper for cardano-cli for working with cardano cluster
Author-email: Martin Kourim <martin.kourim@iohk.io>
License-Expression: Apache-2.0
Project-URL: homepage, https://github.com/input-output-hk/cardano-clusterlib-py
Project-URL: documentation, https://cardano-clusterlib-py.readthedocs.io/
Project-URL: repository, https://github.com/input-output-hk/cardano-clusterlib-py
Keywords: cardano,cardano-node,cardano-cli,cardano-node-tests
Classifier: Topic :: Software Development :: Libraries :: Python Modules
Classifier: Programming Language :: Python :: 3
Classifier: Programming Language :: Python :: 3.9
Classifier: Programming Language :: Python :: 3.10
Classifier: Programming Language :: Python :: 3.11
Classifier: Programming Language :: Python :: 3.12
Classifier: Programming Language :: Python :: 3.13
Classifier: Intended Audience :: Developers
Requires-Python: >=3.9
License-File: LICENSE
Requires-Dist: packaging
Dynamic: license-file
